facedetect/__init__.py
facedetect/lib.py
facedetectpy-1.0.5.data/scripts/facedetect
facedetectpy-1.0.5.dist-info/DESCRIPTION.rst
facedetectpy-1.0.5.dist-info/METADATA
facedetectpy-1.0.5.dist-info/RECORD
facedetectpy-1.0.5.dist-info/WHEEL
facedetectpy-1.0.5.dist-info/metadata.json
facedetectpy-1.0.5.dist-info/top_level.txt
