Metadata-Version: 2.0
Name: facedetectpy
Version: 1.0.5
Summary: Facedetect Library for Python (Originally by wave++ "Yuri D'Elia" <wavexx@thregr.org>)
Home-page: https://github.com/picovico/facedetect-py
Author: Picovico (originally authored by wave++)
Author-email: info@picovico.com
License: GPLv2+
Keywords: facedetect wave++ picovico slideshow-maker video-maker sdk
Platform: UNKNOWN
Classifier: Development Status :: 5 - Production/Stable
Classifier: Intended Audience :: Developers
Classifier: Topic :: Software Development :: Build Tools
Classifier: License :: OSI Approved :: GNU General Public License v2 or later (GPLv2+)
Classifier: Programming Language :: Python :: 2
Classifier: Programming Language :: Python :: 2.6
Classifier: Programming Language :: Python :: 2.7
Classifier: Programming Language :: Python :: 3
Classifier: Programming Language :: Python :: 3.2
Classifier: Programming Language :: Python :: 3.3
Classifier: Programming Language :: Python :: 3.4
Classifier: Programming Language :: Python :: 3.5
Requires-Dist: six
Requires-Dist: numpy
Requires-Dist: opencv-python
